pwinput/__init__.py
pwinput/__main__.py
pwinput_eoleedi-1.0.3.post1.dist-info/licenses/LICENSE.txt
pwinput_eoleedi-1.0.3.post1.dist-info/METADATA
pwinput_eoleedi-1.0.3.post1.dist-info/WHEEL
pwinput_eoleedi-1.0.3.post1.dist-info/top_level.txt
pwinput_eoleedi-1.0.3.post1.dist-info/RECORD
