Metadata-Version: 2.4
Name: pwinput-eoleedi
Version: 1.0.3.post1
Summary: A cross-platform Python module that displays **** for password input. Works on Windows, unlike getpass. Formerly called stdiomask. (custom fork by Eoleedi
Home-page: https://github.com/eoleedi/pwinput
Author: Fong-Chun Tsai
Author-email: eoleedimin@gmail.com
License: MIT
Classifier: License :: OSI Approved :: MIT License
Classifier: Programming Language :: Python
Classifier: Programming Language :: Python :: 2
Classifier: Programming Language :: Python :: 2.7
Classifier: Programming Language :: Python :: 3
Classifier: Programming Language :: Python :: 3.4
Classifier: Programming Language :: Python :: 3.5
Classifier: Programming Language :: Python :: 3.6
Classifier: Programming Language :: Python :: 3.7
Classifier: Programming Language :: Python :: 3.8
Classifier: Programming Language :: Python :: 3.9
License-File: LICENSE.txt
Dynamic: author
Dynamic: author-email
Dynamic: classifier
Dynamic: description
Dynamic: description-content-type
Dynamic: home-page
Dynamic: keywords
Dynamic: license
Dynamic: license-file
Dynamic: summary
